flask_ldapconn/__init__.py
flask_ldapconn/attribute.py
flask_ldapconn/entry.py
flask_ldapconn/query.py
Flask_LDAPConn-0.10.2.dist-info/LICENSE
Flask_LDAPConn-0.10.2.dist-info/METADATA
Flask_LDAPConn-0.10.2.dist-info/WHEEL
Flask_LDAPConn-0.10.2.dist-info/top_level.txt
Flask_LDAPConn-0.10.2.dist-info/RECORD
