Metadata-Version: 2.1
Name: Flask-LDAPConn
Version: 0.10.2
Summary: Pure python, LDAP connection and ORM for Flask Applications
Home-page: http://github.com/rroemhild/flask-ldapconn
Author: Rafael Römhild
Author-email: rafael@roemhild.de
License: BSD
Keywords: flask ldap ldap3 orm
Platform: any
Classifier: Development Status :: 5 - Production/Stable
Classifier: Environment :: Web Environment
Classifier: Intended Audience :: Developers
Classifier: License :: OSI Approved :: BSD License
Classifier: Operating System :: OS Independent
Classifier: Programming Language :: Python :: 3.5
Classifier: Programming Language :: Python :: 3.6
Classifier: Programming Language :: Python :: 3.7
Classifier: Framework :: Flask
Classifier: Topic :: Internet :: WWW/HTTP :: Dynamic Content
Classifier: Topic :: Software Development :: Libraries :: Python Modules
License-File: LICENSE
Requires-Dist: Flask >=0.12
Requires-Dist: ldap3 >=2.3
